main/__init__.py
main/casino_bot.py
main/jit_exchange_lag_finder.py
main/legacy_strategy_code.py
main/utility_functions.py
tests/__init__.py
tests/test_legacy_strategy_code.py
tests/test_utility_functions.py
crypto_trader_ArtifaxXx-0.0.1.dist-info/LICENSE
crypto_trader_ArtifaxXx-0.0.1.dist-info/METADATA
crypto_trader_ArtifaxXx-0.0.1.dist-info/WHEEL
crypto_trader_ArtifaxXx-0.0.1.dist-info/top_level.txt
crypto_trader_ArtifaxXx-0.0.1.dist-info/RECORD
