Metadata-Version: 2.1
Name: crypto-trader-ArtifaxXx
Version: 0.0.1
Summary: A pet crypto trading project
Home-page: https://github.com/ArtifaxXx/crypto-trader
Author: ArtifaxXx
Author-email: 
License: UNKNOWN
Platform: UNKNOWN
Classifier: Programming Language :: Python :: 3
Classifier: License :: OSI Approved :: MIT License
Classifier: Operating System :: OS Independent
Requires-Python: >=3.7
